examples/titanic/__init__.py
examples/titanic/run_tests.py
examples/titanic/setup_environment.py
preql_nlp/__init__.py
preql_nlp/constants.py
preql_nlp/core.py
preql_nlp/enums.py
preql_nlp/exceptions.py
preql_nlp/helpers.py
preql_nlp/main.py
preql_nlp/main_v2.py
preql_nlp/models.py
preql_nlp/monkeypatch.py
preql_nlp/py.typed
preql_nlp/tokenization.py
preql_nlp/cache_providers/__init__.py
preql_nlp/cache_providers/base.py
preql_nlp/cache_providers/local_sqlite.py
preql_nlp/prompts/__init__.py
preql_nlp/prompts/prompt_executor.py
preql_nlp/prompts/prompt_final_concepts.jinja2
preql_nlp/prompts/prompt_final_concepts_v2.jinja2
preql_nlp/prompts/prompt_query_semantic_groupings.jinja2
preql_nlp/prompts/prompt_refine_filter.jinja2
preql_nlp/prompts/prompt_refine_filter_error.jinja2
preql_nlp/prompts/prompt_semantic_to_tokens.jinja2
pypreql_nlp-0.0.18.dist-info/METADATA
pypreql_nlp-0.0.18.dist-info/WHEEL
pypreql_nlp-0.0.18.dist-info/top_level.txt
pypreql_nlp-0.0.18.dist-info/RECORD
