Metadata-Version: 2.1
Name: pypreql-nlp
Version: 0.0.18
Summary: NLP interface for pypreql.
Home-page: 
Author: 
Author-email: pypreql-community@gmail.com
Classifier: Programming Language :: Python
Classifier: Programming Language :: Python :: 3
Classifier: Programming Language :: Python :: 3.9
Classifier: Programming Language :: Python :: 3.10
Classifier: Programming Language :: Python :: 3.11
Requires-Dist: pypreql >=0.0.1.96
Requires-Dist: promptimize
Requires-Dist: pandas
Requires-Dist: openai
Requires-Dist: langchain-openai
Requires-Dist: langchain-community
Requires-Dist: mediawikiapi
Requires-Dist: wikibase-rest-api-client
